acmebot/__init__.py
acmebot/acmebot.py
acmebot-2.17.0.dist-info/licenses/LICENSE
acmebot-2.17.0.dist-info/METADATA
acmebot-2.17.0.dist-info/WHEEL
acmebot-2.17.0.dist-info/entry_points.txt
acmebot-2.17.0.dist-info/top_level.txt
acmebot-2.17.0.dist-info/RECORD
