Metadata-Version: 2.4
Name: acmebot
Version: 2.17.0
Summary: ACME protocol automatic certitificate manager
Author-email: Peter Linss <peter@linss.com>
Project-URL: homepage, https://acmebot.org
Requires-Python: >=3.8
License-File: LICENSE
Requires-Dist: appdirs<2.0.0,>=1.4.3
Requires-Dist: pyparsing<3.2.0,>=2.2.0
Requires-Dist: packaging>=16.8
Requires-Dist: pyOpenSSL>=17.5.0
Requires-Dist: py3dns<5.0.0,>=3.1.0
Requires-Dist: cryptography>=2.6.1
Requires-Dist: asn1crypto<2.0.0,>=0.24.0
Requires-Dist: acme<4.0.0,>=2.0.0
Requires-Dist: PyYAML<7.0.0,>=3.1
Requires-Dist: josepy<2.0.0,>=1.0.0
Provides-Extra: dev
Requires-Dist: types-PyYAML; extra == "dev"
Requires-Dist: mypy; extra == "dev"
Requires-Dist: flake8; extra == "dev"
Requires-Dist: flake8-annotations; extra == "dev"
Requires-Dist: flake8-bandit; extra == "dev"
Requires-Dist: flake8-bugbear; extra == "dev"
Requires-Dist: flake8-commas; extra == "dev"
Requires-Dist: flake8-comprehensions; extra == "dev"
Requires-Dist: flake8-continuation; extra == "dev"
Requires-Dist: flake8-datetimez; extra == "dev"
Requires-Dist: flake8-docstrings; extra == "dev"
Requires-Dist: flake8-import-order; extra == "dev"
Requires-Dist: flake8-literal; extra == "dev"
Requires-Dist: flake8-modern-annotations; extra == "dev"
Requires-Dist: flake8-noqa; extra == "dev"
Requires-Dist: flake8-pyproject; extra == "dev"
Requires-Dist: flake8-requirements; extra == "dev"
Requires-Dist: flake8-typechecking-import; extra == "dev"
Requires-Dist: flake8-use-fstring; extra == "dev"
Requires-Dist: pep8-naming; extra == "dev"
Dynamic: license-file
